{
  "name": "meme",
  "fallback": "minecraft:empty",
  "elements": [
    {
      "weight": 3,
      "element": {
        "location": "shioh:outcast_villager/clearing1",
        "processors": "minecraft:plains_streets",
        "projection": "terrain_matching",
        "element_type": "minecraft:legacy_single_pool_element"
      }
    },
    {
      "weight": 3,
      "element": {
        "location": "shioh:outcast_villager/clearing2",
        "processors": "minecraft:plains_streets",
        "projection": "terrain_matching",
        "element_type": "minecraft:legacy_single_pool_element"
      }
    },
    {
      "weight": 3,
      "element": {
        "location": "shioh:outcast_villager/clearing3",
        "processors": "minecraft:plains_streets",
        "projection": "terrain_matching",
        "element_type": "minecraft:legacy_single_pool_element"
      }
    },
    {
      "weight": 3,
      "element": {
        "location": "shioh:outcast_villager/clearing4",
        "processors": "minecraft:plains_streets",
        "projection": "terrain_matching",
        "element_type": "minecraft:legacy_single_pool_element"
      }
    },
    {
      "weight": 3,
      "element": {
        "location": "shioh:outcast_villager/clearing5",
        "processors": "minecraft:plains_streets",
        "projection": "terrain_matching",
        "element_type": "minecraft:legacy_single_pool_element"
      }
    },
    {
      "weight": 3,
      "element": {
        "location": "shioh:outcast_villager/clearing6",
        "processors": "minecraft:plains_streets",
        "projection": "terrain_matching",
        "element_type": "minecraft:legacy_single_pool_element"
      }
    },
    {
      "weight": 3,
      "element": {
        "location": "shioh:outcast_villager/clearing7",
        "processors": "minecraft:plains_streets",
        "projection": "terrain_matching",
        "element_type": "minecraft:legacy_single_pool_element"
      }
    },
    {
      "weight": 3,
      "element": {
        "location": "shioh:outcast_villager/clearing8",
        "processors": "minecraft:plains_streets",
        "projection": "terrain_matching",
        "element_type": "minecraft:legacy_single_pool_element"
      }
    }
  ]
}
