{
  "feature": {
    "type": "minecraft:disk",
    "config": {
      "state_provider": {
        "fallback": {
          "type": "minecraft:simple_state_provider",
          "state": {
            "Name": "minecraft:grass_block"
          }
        },
        "rules": []
      },
      "target": {
        "type": "minecraft:matching_blocks",
        "blocks": [
          "minecraft:end_stone"
        ]
      },
      "radius": {
        "type": "minecraft:uniform",
          "min_inclusive": 7,
          "max_inclusive": 7
      },
      "half_height": 4
    }
  },
  "placement": [
    {
      "type": "minecraft:count",
      "count": 190
    },
    {
      "type": "minecraft:height_range",
      "height": {
        "absolute": 0
      }
    },
    {
      "type": "minecraft:in_square"
    },
    {
      "type": "minecraft:heightmap",
      "heightmap": "WORLD_SURFACE_WG"
    },
    {
      "type": "minecraft:block_predicate_filter",
      "predicate": {
        "type": "minecraft:matching_blocks",
        "blocks": [
          "minecraft:air",
          "minecraft:basalt",
          "minecraft:end_stone"
        ]
      }
    }
  ]
}
