{
	"credit": "Made with Blockbench",
	"parent": "item",
	"texture_size": [32, 32],
	"textures": {
		"0": "./kunai",
		"particle": "./kunai"
	},
	"elements": [
		{
			"name": "kunai_0",
			"from": [8.32, 9.92, 4.8],
			"to": [8.96, 11.2, 6.08],
			"rotation": {"angle": 0, "axis": "y", "origin": [8.96, 2.88, 2.88]},
			"faces": {
				"north": {"uv": [3, 3, 4, 5], "texture": "#0"},
				"east": {"uv": [5, 3, 3, 5], "texture": "#0"},
				"south": {"uv": [4, 3, 5, 5], "texture": "#0"},
				"west": {"uv": [3, 3, 5, 5], "texture": "#0"},
				"up": {"uv": [3, 3, 5, 4], "rotation": 90, "texture": "#0"},
				"down": {"uv": [3, 4, 5, 5], "rotation": 270, "texture": "#0"}
			}
		},
		{
			"name": "kunai_1",
			"from": [8.32, 7.36, 6.08],
			"to": [8.96, 10.56, 7.36],
			"rotation": {"angle": 0, "axis": "y", "origin": [8.96, 2.88, 2.88]},
			"faces": {
				"north": {"uv": [5, 4, 6, 9], "texture": "#0"},
				"east": {"uv": [7, 4, 5, 9], "texture": "#0"},
				"south": {"uv": [6, 4, 7, 9], "texture": "#0"},
				"west": {"uv": [5, 4, 7, 9], "texture": "#0"},
				"up": {"uv": [5, 4, 7, 5], "rotation": 90, "texture": "#0"},
				"down": {"uv": [5, 8, 7, 9], "rotation": 270, "texture": "#0"}
			}
		},
		{
			"name": "kunai_2",
			"from": [8.32, 8.64, 5.44],
			"to": [8.96, 9.92, 6.08],
			"rotation": {"angle": 0, "axis": "y", "origin": [8.96, 2.88, 2.88]},
			"faces": {
				"north": {"uv": [4, 5, 5, 7], "texture": "#0"},
				"east": {"uv": [5, 5, 4, 7], "texture": "#0"},
				"south": {"uv": [4, 5, 5, 7], "texture": "#0"},
				"west": {"uv": [4, 5, 5, 7], "texture": "#0"},
				"up": {"uv": [4, 5, 5, 6], "rotation": 90, "texture": "#0"},
				"down": {"uv": [4, 6, 5, 7], "rotation": 270, "texture": "#0"}
			}
		},
		{
			"name": "kunai_3",
			"from": [8.32, 6.72, 7.36],
			"to": [8.96, 9.92, 8.64],
			"rotation": {"angle": 0, "axis": "y", "origin": [8.96, 2.88, 2.88]},
			"faces": {
				"north": {"uv": [7, 5, 8, 10], "texture": "#0"},
				"east": {"uv": [9, 5, 7, 10], "texture": "#0"},
				"south": {"uv": [8, 5, 9, 10], "texture": "#0"},
				"west": {"uv": [7, 5, 9, 10], "texture": "#0"},
				"up": {"uv": [7, 5, 9, 6], "rotation": 90, "texture": "#0"},
				"down": {"uv": [7, 9, 9, 10], "rotation": 270, "texture": "#0"}
			}
		},
		{
			"name": "kunai_4",
			"from": [8.32, 6.08, 8.64],
			"to": [8.96, 9.28, 9.28],
			"rotation": {"angle": 0, "axis": "y", "origin": [8.96, 2.88, 2.88]},
			"faces": {
				"north": {"uv": [9, 6, 10, 11], "texture": "#0"},
				"east": {"uv": [10, 6, 9, 11], "texture": "#0"},
				"south": {"uv": [9, 6, 10, 11], "texture": "#0"},
				"west": {"uv": [9, 6, 10, 11], "texture": "#0"},
				"up": {"uv": [9, 6, 10, 7], "rotation": 90, "texture": "#0"},
				"down": {"uv": [9, 10, 10, 11], "rotation": 270, "texture": "#0"}
			}
		},
		{
			"name": "kunai_5",
			"from": [8.32, 6.72, 6.72],
			"to": [8.96, 7.36, 7.36],
			"rotation": {"angle": 0, "axis": "y", "origin": [8.96, 2.88, 2.88]},
			"faces": {
				"north": {"uv": [6, 9, 7, 10], "texture": "#0"},
				"east": {"uv": [7, 9, 6, 10], "texture": "#0"},
				"south": {"uv": [6, 9, 7, 10], "texture": "#0"},
				"west": {"uv": [6, 9, 7, 10], "texture": "#0"},
				"up": {"uv": [6, 9, 7, 10], "rotation": 90, "texture": "#0"},
				"down": {"uv": [6, 9, 7, 10], "rotation": 270, "texture": "#0"}
			}
		},
		{
			"name": "kunai_6",
			"from": [8.32, 4.8, 9.28],
			"to": [8.96, 7.36, 9.92],
			"rotation": {"angle": 0, "axis": "y", "origin": [8.96, 2.88, 2.88]},
			"faces": {
				"north": {"uv": [10, 9, 11, 13], "texture": "#0"},
				"east": {"uv": [11, 9, 10, 13], "texture": "#0"},
				"south": {"uv": [10, 9, 11, 13], "texture": "#0"},
				"west": {"uv": [10, 9, 11, 13], "texture": "#0"},
				"up": {"uv": [10, 9, 11, 10], "rotation": 90, "texture": "#0"},
				"down": {"uv": [10, 12, 11, 13], "rotation": 270, "texture": "#0"}
			}
		},
		{
			"name": "kunai_7",
			"from": [8.32, 5.44, 9.92],
			"to": [8.96, 6.72, 11.2],
			"rotation": {"angle": 0, "axis": "y", "origin": [8.96, 2.88, 2.88]},
			"faces": {
				"north": {"uv": [11, 10, 12, 12], "texture": "#0"},
				"east": {"uv": [13, 10, 11, 12], "texture": "#0"},
				"south": {"uv": [12, 10, 13, 12], "texture": "#0"},
				"west": {"uv": [11, 10, 13, 12], "texture": "#0"},
				"up": {"uv": [11, 10, 13, 11], "rotation": 90, "texture": "#0"},
				"down": {"uv": [11, 11, 13, 12], "rotation": 270, "texture": "#0"}
			}
		},
		{
			"name": "kunai_8",
			"from": [8.32, 4.8, 9.92],
			"to": [8.96, 5.44, 10.56],
			"rotation": {"angle": 0, "axis": "y", "origin": [8.96, 2.88, 2.88]},
			"faces": {
				"north": {"uv": [11, 12, 12, 13], "texture": "#0"},
				"east": {"uv": [12, 12, 11, 13], "texture": "#0"},
				"south": {"uv": [11, 12, 12, 13], "texture": "#0"},
				"west": {"uv": [11, 12, 12, 13], "texture": "#0"},
				"up": {"uv": [11, 12, 12, 13], "rotation": 90, "texture": "#0"},
				"down": {"uv": [11, 12, 12, 13], "rotation": 270, "texture": "#0"}
			}
		}
	],
	"gui_light": "front",
	"display": {
		"thirdperson_righthand": {
			"rotation": [-6.33, 15.29, 83.74],
			"translation": [-3.75, -2.25, -0.25]
		},
		"thirdperson_lefthand": {
			"rotation": [-2, 0, 89],
			"translation": [-3, -0.75, -2.25]
		},
		"firstperson_righthand": {
			"rotation": [-132.13, 82.68, 82.39],
			"translation": [-7.25, 5.5, 2.25]
		},
		"firstperson_lefthand": {
			"rotation": [34.06, -0.14, -67.58],
			"translation": [2.75, 1.5, 0]
		},
		"ground": {
			"rotation": [0, 0, -90],
			"translation": [-1, -1.25, 0]
		},
		"gui": {
			"rotation": [0, 90, 0],
			"translation": [0, -1, 0],
			"scale": [2.14, 2.13, 2.08]
		},
		"fixed": {
			"rotation": [0, -90, 0],
			"translation": [0.25, -0.75, -2],
			"scale": [2, 2, 2]
		}
	},
	"groups": [
		{
			"name": "kunai",
			"origin": [8, 8, 8],
			"color": 0,
			"nbt": "{}",
			"children": [0, 1, 2, 3, 4, 5, 6, 7, 8]
		}
	]
}